zabel/palette/__init__.py
zabel/palette/async.py
zabel/palette/date.py
zabel/palette/db.py
zabel/palette/html.py
zabel/palette/http.py
zabel/palette/i18n.py
zabel/palette/misc.py
zabel/palette/text.py
zabel/palette/timeline.py
zabel_palette-0.1.0.dist-info/LICENSE.txt
zabel_palette-0.1.0.dist-info/METADATA
zabel_palette-0.1.0.dist-info/WHEEL
zabel_palette-0.1.0.dist-info/top_level.txt
zabel_palette-0.1.0.dist-info/RECORD
