Metadata-Version: 2.1
Name: zabel-palette
Version: 0.1.0
Summary: The Zabel **palette** library
Home-page: https://github.com/engie-group/zabel
Author: Martin Lafaix
Author-email: martin.lafaix@external.engie.com
License: Eclipse Public License 2.0
Classifier: Development Status :: 3 - Alpha
Classifier: Programming Language :: Python :: 3
Classifier: License :: OSI Approved :: Eclipse Public License 2.0 (EPL-2.0)
Classifier: Operating System :: OS Independent
Classifier: Topic :: Utilities
Requires-Python: >= 3.8.0
License-File: LICENSE.txt
Provides-Extra: all
Requires-Dist: psycopg2 ; extra == 'all'
